swampdragon_upload
