Metadata-Version: 1.1
Name: SwampDragon-fileupload
Version: 0.1.2
Summary: File upload handler for SwampDragon
Home-page: https://github.com/jonashagstedt/swampdragon-fileupload
Author: Jonas Hagstedt
Author-email: hagstedt@gmail.com
License: BSD
Keywords: SwampDragon,file upload
Platform: UNKNOWN
Classifier: Development Status :: 4 - Beta
Classifier: License :: OSI Approved :: BSD License
Classifier: Programming Language :: Python :: 2.7
Classifier: Programming Language :: Python :: 3
Classifier: Programming Language :: Python :: 3.3
Classifier: Programming Language :: Python :: 3.4
